Metadata-Version: 2.1
Name: odoo-addon-product_attribute_value_archive
Version: 18.0.1.0.1
Requires-Python: >=3.10
Requires-Dist: odoo==18.0.*
Summary: Allows to archive a `product.attribute.value` referenced by archived `product.product`.
Home-page: https://github.com/OCA/product-variant
License: AGPL-3
Author: Camptocamp SA, Odoo Community Association (OCA)
Author-email: support@odoo-community.org
Classifier: Programming Language :: Python
Classifier: Framework :: Odoo
Classifier: Framework :: Odoo :: 18.0
Classifier: License :: OSI Approved :: GNU Affero General Public License v3
